lora/__init__.py
lora/tools.py
lora/util.py
lora-0.3.0.dist-info/DESCRIPTION.rst
lora-0.3.0.dist-info/METADATA
lora-0.3.0.dist-info/RECORD
lora-0.3.0.dist-info/WHEEL
lora-0.3.0.dist-info/metadata.json
lora-0.3.0.dist-info/top_level.txt
